libkratos-runtime.so
kratos_runtime/util.py
kratos_runtime/debugger.py
kratos_runtime/tester.py
kratos_runtime/__init__.py
kratos_runtime-0.0.8.dist-info/top_level.txt
kratos_runtime-0.0.8.dist-info/RECORD
kratos_runtime-0.0.8.dist-info/METADATA
kratos_runtime-0.0.8.dist-info/WHEEL
