Metadata-Version: 2.1
Name: kratos-runtime
Version: 0.0.8
Summary: Kratos runtime for debugging
Home-page: https://github.com/Kuree/kratos-runtime
Author: Keyi Zhang
Author-email: keyi@cs.stanford.edu
License: UNKNOWN
Platform: UNKNOWN
